sanic/__init__.py
sanic/__main__.py
sanic/__version__.py
sanic/app.py
sanic/asgi.py
sanic/blueprint_group.py
sanic/blueprints.py
sanic/compat.py
sanic/config.py
sanic/constants.py
sanic/errorpages.py
sanic/exceptions.py
sanic/headers.py
sanic/helpers.py
sanic/log.py
sanic/middleware.py
sanic/py.typed
sanic/router.py
sanic/signals.py
sanic/simple.py
sanic/utils.py
sanic/views.py
sanic/application/__init__.py
sanic/application/constants.py
sanic/application/ext.py
sanic/application/logo.py
sanic/application/motd.py
sanic/application/spinner.py
sanic/application/state.py
sanic/base/__init__.py
sanic/base/meta.py
sanic/base/root.py
sanic/cli/__init__.py
sanic/cli/app.py
sanic/cli/arguments.py
sanic/cli/base.py
sanic/cli/console.py
sanic/cli/daemon.py
sanic/cli/executor.py
sanic/cli/inspector.py
sanic/cli/inspector_client.py
sanic/cookies/__init__.py
sanic/cookies/request.py
sanic/cookies/response.py
sanic/handlers/__init__.py
sanic/handlers/content_range.py
sanic/handlers/directory.py
sanic/handlers/error.py
sanic/http/__init__.py
sanic/http/constants.py
sanic/http/http1.py
sanic/http/http3.py
sanic/http/stream.py
sanic/http/tls/__init__.py
sanic/http/tls/context.py
sanic/http/tls/creators.py
sanic/logging/__init__.py
sanic/logging/color.py
sanic/logging/default.py
sanic/logging/deprecation.py
sanic/logging/filter.py
sanic/logging/formatter.py
sanic/logging/loggers.py
sanic/logging/setup.py
sanic/mixins/__init__.py
sanic/mixins/base.py
sanic/mixins/commands.py
sanic/mixins/exceptions.py
sanic/mixins/listeners.py
sanic/mixins/middleware.py
sanic/mixins/routes.py
sanic/mixins/signals.py
sanic/mixins/startup.py
sanic/mixins/static.py
sanic/models/__init__.py
sanic/models/asgi.py
sanic/models/ctx_types.py
sanic/models/futures.py
sanic/models/handler_types.py
sanic/models/http_types.py
sanic/models/protocol_types.py
sanic/models/server_types.py
sanic/pages/__init__.py
sanic/pages/base.py
sanic/pages/css.py
sanic/pages/directory_page.py
sanic/pages/error.py
sanic-25.12.0.dist-info/licenses/LICENSE
sanic-25.12.0.dist-info/METADATA
sanic-25.12.0.dist-info/WHEEL
sanic-25.12.0.dist-info/entry_points.txt
sanic-25.12.0.dist-info/top_level.txt
sanic-25.12.0.dist-info/RECORD
