Metadata-Version: 2.4
Name: sanic
Version: 25.12.0
Summary: A web server and web framework that's written to go fast. Build fast. Run fast.
Home-page: http://github.com/sanic-org/sanic/
Author: Sanic Community
Author-email: admhpkns@gmail.com
License: MIT
Platform: any
Classifier: Development Status :: 4 - Beta
Classifier: Environment :: Web Environment
Classifier: License :: OSI Approved :: MIT License
Classifier: Programming Language :: Python :: 3.10
Classifier: Programming Language :: Python :: 3.11
Classifier: Programming Language :: Python :: 3.12
Classifier: Programming Language :: Python :: 3.13
Classifier: Programming Language :: Python :: 3.14
Requires-Python: >=3.10
License-File: LICENSE
Requires-Dist: sanic-routing>=23.12.0
Requires-Dist: httptools>=0.0.10
Requires-Dist: uvloop>=0.15.0; sys_platform != "win32" and implementation_name == "cpython"
Requires-Dist: ujson>=1.35; sys_platform != "win32" and implementation_name == "cpython"
Requires-Dist: aiofiles>=0.6.0
Requires-Dist: websockets>=10.0
Requires-Dist: multidict<7.0,>=5.0
Requires-Dist: html5tagger>=1.2.1
Requires-Dist: tracerite>=2.2.0
Requires-Dist: typing-extensions>=4.4.0
Requires-Dist: setuptools>=70.1.0
Provides-Extra: test
Requires-Dist: sanic-testing>=23.6.0; extra == "test"
Requires-Dist: pytest>=8.2.2; extra == "test"
Requires-Dist: pytest-xdist>=3.5.0; extra == "test"
Requires-Dist: pytest-cov>=4.0.0; extra == "test"
Requires-Dist: coverage; extra == "test"
Requires-Dist: beautifulsoup4; extra == "test"
Requires-Dist: pytest-sanic; extra == "test"
Requires-Dist: pytest-benchmark; extra == "test"
Requires-Dist: chardet==3.*; extra == "test"
Requires-Dist: ruff; extra == "test"
Requires-Dist: bandit; extra == "test"
Requires-Dist: mypy; extra == "test"
Requires-Dist: docutils; extra == "test"
Requires-Dist: pygments; extra == "test"
Requires-Dist: uvicorn; extra == "test"
Requires-Dist: slotscheck<1,>=0.8.0; extra == "test"
Requires-Dist: types-ujson; (sys_platform != "win32" and implementation_name == "cpython") and extra == "test"
Provides-Extra: dev
Requires-Dist: sanic-testing>=23.6.0; extra == "dev"
Requires-Dist: pytest>=8.2.2; extra == "dev"
Requires-Dist: pytest-xdist>=3.5.0; extra == "dev"
Requires-Dist: pytest-cov>=4.0.0; extra == "dev"
Requires-Dist: coverage; extra == "dev"
Requires-Dist: beautifulsoup4; extra == "dev"
Requires-Dist: pytest-sanic; extra == "dev"
Requires-Dist: pytest-benchmark; extra == "dev"
Requires-Dist: chardet==3.*; extra == "dev"
Requires-Dist: ruff; extra == "dev"
Requires-Dist: bandit; extra == "dev"
Requires-Dist: mypy; extra == "dev"
Requires-Dist: docutils; extra == "dev"
Requires-Dist: pygments; extra == "dev"
Requires-Dist: uvicorn; extra == "dev"
Requires-Dist: slotscheck<1,>=0.8.0; extra == "dev"
Requires-Dist: types-ujson; (sys_platform != "win32" and implementation_name == "cpython") and extra == "dev"
Requires-Dist: cryptography; extra == "dev"
Requires-Dist: tox; extra == "dev"
Requires-Dist: towncrier; extra == "dev"
Provides-Extra: docs
Requires-Dist: sphinx>=2.1.2; extra == "docs"
Requires-Dist: sphinx_rtd_theme>=0.4.3; extra == "docs"
Requires-Dist: docutils; extra == "docs"
Requires-Dist: pygments; extra == "docs"
Requires-Dist: m2r2; extra == "docs"
Requires-Dist: enum-tools[sphinx]; extra == "docs"
Requires-Dist: mistune>=2.0.0; extra == "docs"
Requires-Dist: autodocsumm>=0.2.11; extra == "docs"
Requires-Dist: msgspec; extra == "docs"
Requires-Dist: python-frontmatter; extra == "docs"
Requires-Dist: docstring-parser; extra == "docs"
Requires-Dist: libsass; extra == "docs"
Provides-Extra: all
Requires-Dist: msgspec; extra == "all"
Requires-Dist: towncrier; extra == "all"
Requires-Dist: uvicorn; extra == "all"
Requires-Dist: sanic-testing>=23.6.0; extra == "all"
Requires-Dist: enum-tools[sphinx]; extra == "all"
Requires-Dist: pytest-cov>=4.0.0; extra == "all"
Requires-Dist: slotscheck<1,>=0.8.0; extra == "all"
Requires-Dist: bandit; extra == "all"
Requires-Dist: m2r2; extra == "all"
Requires-Dist: pygments; extra == "all"
Requires-Dist: sphinx>=2.1.2; extra == "all"
Requires-Dist: types-ujson; (sys_platform != "win32" and implementation_name == "cpython") and extra == "all"
Requires-Dist: coverage; extra == "all"
Requires-Dist: chardet==3.*; extra == "all"
Requires-Dist: autodocsumm>=0.2.11; extra == "all"
Requires-Dist: tox; extra == "all"
Requires-Dist: mypy; extra == "all"
Requires-Dist: cryptography; extra == "all"
Requires-Dist: docutils; extra == "all"
Requires-Dist: beautifulsoup4; extra == "all"
Requires-Dist: libsass; extra == "all"
Requires-Dist: python-frontmatter; extra == "all"
Requires-Dist: pytest-xdist>=3.5.0; extra == "all"
Requires-Dist: sphinx_rtd_theme>=0.4.3; extra == "all"
Requires-Dist: docstring-parser; extra == "all"
Requires-Dist: pytest>=8.2.2; extra == "all"
Requires-Dist: pytest-sanic; extra == "all"
Requires-Dist: ruff; extra == "all"
Requires-Dist: mistune>=2.0.0; extra == "all"
Requires-Dist: pytest-benchmark; extra == "all"
Provides-Extra: ext
Requires-Dist: sanic-ext; extra == "ext"
Provides-Extra: http3
Requires-Dist: aioquic; extra == "http3"
Dynamic: author
Dynamic: author-email
Dynamic: classifier
Dynamic: description
Dynamic: home-page
Dynamic: license
Dynamic: license-file
Dynamic: platform
Dynamic: provides-extra
Dynamic: requires-dist
Dynamic: requires-python
Dynamic: summary
